{
  "id": "253:18",
  "name": "4. main/ scan-qrcode",
  "type": "FRAME",
  "scrollBehavior": "SCROLLS",
  "children": [
    {
      "id": "253:194",
      "name": "bottom-menu",
      "type": "GROUP",
      "scrollBehavior": "SCROLLS",
      "children": [
        {
          "id": "253:195",
          "name": "nav-bottom",
          "type": "RECTANGLE",
          "scrollBehavior": "SCROLLS",
          "blendMode": "PASS_THROUGH",
          "fills": [
            {
              "blendMode": "NORMAL",
              "type": "SOLID",
              "color": {
                "r": 0.9882352948188782,
                "g": 0.9921568632125854,
                "b": 0.9921568632125854,
                "a": 1
              }
            }
          ],
          "strokes": [
            {
              "blendMode": "NORMAL",
              "type": "SOLID",
              "color": {
                "r": 0.45490196347236633,
                "g": 0.5411764979362488,
                "b": 0.6470588445663452,
                "a": 1
              }
            }
          ],
          "strokeWeight": 1,
          "strokeAlign": "OUTSIDE",
          "absoluteBoundingBox": {
            "x": 0,
            "y": 3814,
            "width": 414,
            "height": 66
          },
          "absoluteRenderBounds": {
            "x": 0,
            "y": 3813,
            "width": 414,
            "height": 67
          },
          "constraints": {
            "vertical": "TOP",
            "horizontal": "LEFT"
          },
          "effects": [],
          "interactions": [],
          "complexStrokeProperties": {
            "strokeType": "BASIC"
          }
        },
        {
          "id": "253:196",
          "name": "ic-search",
          "type": "FRAME",
          "scrollBehavior": "SCROLLS",
          "children": [
            {
              "id": "253:197",
              "name": "Group",
              "type": "GROUP",
              "scrollBehavior": "SCROLLS",
              "children": [
                {
                  "id": "253:198",
                  "name": "Vector",
                  "type": "VECTOR",
                  "scrollBehavior": "SCROLLS",
                  "blendMode": "PASS_THROUGH",
                  "fills": [
                    {
                      "blendMode": "NORMAL",
                      "type": "SOLID",
                      "color": {
                        "r": 0.8823529481887817,
                        "g": 0.8901960849761963,
                        "b": 0.9019607901573181,
                        "a": 1
                      }
                    }
                  ],
                  "strokes": [],
                  "strokeWeight": 32,
                  "strokeAlign": "INSIDE",
                  "absoluteBoundingBox": {
                    "x": 186,
                    "y": 3835,
                    "width": 24,
                    "height": 23.849998474121094
                  },
                  "absoluteRenderBounds": {
                    "x": 186,
                    "y": 3835,
                    "width": 24,
                    "height": 23.85009765625
                  },
                  "constraints": {
                    "vertical": "SCALE",
                    "horizontal": "SCALE"
                  },
                  "effects": [],
                  "interactions": [],
                  "complexStrokeProperties": {
                    "strokeType": "BASIC"
                  }
                }
              ],
              "blendMode": "PASS_THROUGH",
              "clipsContent": false,
              "background": [],
              "fills": [],
              "strokes": [],
              "strokeWeight": 32,
              "strokeAlign": "INSIDE",
              "backgroundColor": {
                "r": 0,
                "g": 0,
                "b": 0,
                "a": 0
              },
              "absoluteBoundingBox": {
                "x": 186,
                "y": 3835,
                "width": 24,
                "height": 23.849998474121094
              },
              "absoluteRenderBounds": {
                "x": 186,
                "y": 3835,
                "width": 24,
                "height": 23.85009765625
              },
              "constraints": {
                "vertical": "SCALE",
                "horizontal": "SCALE"
              },
              "effects": [],
              "interactions": [],
              "complexStrokeProperties": {
                "strokeType": "BASIC"
              }
            }
          ],
          "blendMode": "PASS_THROUGH",
          "clipsContent": true,
          "background": [
            {
              "blendMode": "NORMAL",
              "visible": false,
              "type": "SOLID",
              "color": {
                "r": 1,
                "g": 1,
                "b": 1,
                "a": 1
              }
            }
          ],
          "fills": [
            {
              "blendMode": "NORMAL",
              "visible": false,
              "type": "SOLID",
              "color": {
                "r": 1,
                "g": 1,
                "b": 1,
                "a": 1
              }
            }
          ],
          "strokes": [],
          "strokeWeight": 1,
          "strokeAlign": "INSIDE",
          "backgroundColor": {
            "r": 0,
            "g": 0,
            "b": 0,
            "a": 0
          },
          "absoluteBoundingBox": {
            "x": 186,
            "y": 3835,
            "width": 24,
            "height": 24
          },
          "absoluteRenderBounds": {
            "x": 186,
            "y": 3835,
            "width": 24,
            "height": 24
          },
          "constraints": {
            "vertical": "TOP",
            "horizontal": "LEFT"
          },
          "effects": [],
          "interactions": [],
          "complexStrokeProperties": {
            "strokeType": "BASIC"
          }
        },
        {
          "id": "253:199",
          "name": "qr-code",
          "type": "FRAME",
          "scrollBehavior": "SCROLLS",
          "children": [
            {
              "id": "253:200",
              "name": "Group",
              "type": "GROUP",
              "scrollBehavior": "SCROLLS",
              "children": [
                {
                  "id": "253:201",
                  "name": "Vector",
                  "type": "VECTOR",
                  "scrollBehavior": "SCROLLS",
                  "blendMode": "PASS_THROUGH",
                  "fills": [
                    {
                      "blendMode": "NORMAL",
                      "type": "SOLID",
                      "color": {
                        "r": 0.45490196347236633,
                        "g": 0.5411764979362488,
                        "b": 0.6470588445663452,
                        "a": 1
                      }
                    }
                  ],
                  "strokes": [],
                  "strokeWeight": 21.33333396911621,
                  "strokeAlign": "INSIDE",
                  "absoluteBoundingBox": {
                    "x": 51.30500030517578,
                    "y": 3835,
                    "width": 8.695014953613281,
                    "height": 8.695993423461914
                  },
                  "absoluteRenderBounds": {
                    "x": 51.30500030517578,
                    "y": 3835,
                    "width": 8.694999694824219,
                    "height": 8.696044921875
                  },
                  "constraints": {
                    "vertical": "SCALE",
                    "horizontal": "SCALE"
                  },
                  "effects": [],
                  "interactions": [],
                  "complexStrokeProperties": {
                    "strokeType": "BASIC"
                  }
                }
              ],
              "blendMode": "PASS_THROUGH",
              "clipsContent": false,
              "background": [],
              "fills": [],
              "strokes": [],
              "strokeWeight": 21.33333396911621,
              "strokeAlign": "INSIDE",
              "backgroundColor": {
                "r": 0,
                "g": 0,
                "b": 0,
                "a": 0
              },
              "absoluteBoundingBox": {
                "x": 51.30500030517578,
                "y": 3835,
                "width": 8.695014953613281,
                "height": 8.695993423461914
              },
              "absoluteRenderBounds": {
                "x": 51.30500030517578,
                "y": 3835,
                "width": 8.694999694824219,
                "height": 8.696044921875
              },
              "constraints": {
                "vertical": "SCALE",
                "horizontal": "SCALE"
              },
              "effects": [],
              "interactions": [],
              "complexStrokeProperties": {
                "strokeType": "BASIC"
              }
            },
            {
              "id": "253:202",
              "name": "Group",
              "type": "GROUP",
              "scrollBehavior": "SCROLLS",
              "children": [
                {
                  "id": "253:203",
                  "name": "Vector",
                  "type": "VECTOR",
                  "scrollBehavior": "SCROLLS",
                  "blendMode": "PASS_THROUGH",
                  "fills": [
                    {
                      "blendMode": "NORMAL",
                      "type": "SOLID",
                      "color": {
                        "r": 0.45490196347236633,
                        "g": 0.5411764979362488,
                        "b": 0.6470588445663452,
                        "a": 1
                      }
                    }
                  ],
                  "strokes": [],
                  "strokeWeight": 21.33333396911621,
                  "strokeAlign": "INSIDE",
                  "absoluteBoundingBox": {
                    "x": 36,
                    "y": 3835,
                    "width": 8.694999694824219,
                    "height": 8.696001052856445
                  },
                  "absoluteRenderBounds": {
                    "x": 36,
                    "y": 3835,
                    "width": 8.694999694824219,
                    "height": 8.696044921875
                  },
                  "constraints": {
                    "vertical": "SCALE",
                    "horizontal": "SCALE"
                  },
                  "effects": [],
                  "interactions": [],
                  "complexStrokeProperties": {
                    "strokeType": "BASIC"
                  }
                }
              ],
              "blendMode": "PASS_THROUGH",
              "clipsContent": false,
              "background": [],
              "fills": [],
              "strokes": [],
              "strokeWeight": 21.33333396911621,
              "strokeAlign": "INSIDE",
              "backgroundColor": {
                "r": 0,
                "g": 0,
                "b": 0,
                "a": 0
              },
              "absoluteBoundingBox": {
                "x": 36,
                "y": 3835,
                "width": 8.694999694824219,
                "height": 8.696001052856445
              },
              "absoluteRenderBounds": {
                "x": 36,
                "y": 3835,
                "width": 8.694999694824219,
                "height": 8.696044921875
              },
              "constraints": {
                "vertical": "SCALE",
                "horizontal": "SCALE"
              },
              "effects": [],
              "interactions": [],
              "complexStrokeProperties": {
                "strokeType": "BASIC"
              }
            },
            {
              "id": "253:204",
              "name": "Group",
              "type": "GROUP",
              "scrollBehavior": "SCROLLS",
              "children": [
                {
                  "id": "253:205",
                  "name": "Vector",
                  "type": "VECTOR",
                  "scrollBehavior": "SCROLLS",
                  "blendMode": "PASS_THROUGH",
                  "fills": [
                    {
                      "blendMode": "NORMAL",
                      "type": "SOLID",
                      "color": {
                        "r": 0.45490196347236633,
                        "g": 0.5411764979362488,
                        "b": 0.6470588445663452,
                        "a": 1
                      }
                    }
                  ],
                  "strokes": [],
                  "strokeWeight": 21.33333396911621,
                  "strokeAlign": "INSIDE",
                  "absoluteBoundingBox": {
                    "x": 51.30500030517578,
                    "y": 3850.303955078125,
                    "width": 8.695014953613281,
                    "height": 8.696001052856445
                  },
                  "absoluteRenderBounds": {
                    "x": 51.30500030517578,
                    "y": 3850.303955078125,
                    "width": 8.694999694824219,
                    "height": 8.696044921875
                  },
                  "constraints": {
                    "vertical": "SCALE",
                    "horizontal": "SCALE"
                  },
                  "effects": [],
                  "interactions": [],
                  "complexStrokeProperties": {
                    "strokeType": "BASIC"
                  }
                }
              ],
              "blendMode": "PASS_THROUGH",
              "clipsContent": false,
              "background": [],
              "fills": [],
              "strokes": [],
              "strokeWeight": 21.33333396911621,
              "strokeAlign": "INSIDE",
              "backgroundColor": {
                "r": 0,
                "g": 0,
                "b": 0,
                "a": 0
              },
              "absoluteBoundingBox": {
                "x": 51.30500030517578,
                "y": 3850.303955078125,
                "width": 8.695014953613281,
                "height": 8.696001052856445
              },
              "absoluteRenderBounds": {
                "x": 51.30500030517578,
                "y": 3850.303955078125,
                "width": 8.694999694824219,
                "height": 8.696044921875
              },
              "constraints": {
                "vertical": "SCALE",
                "horizontal": "SCALE"
              },
              "effects": [],
              "interactions": [],
              "complexStrokeProperties": {
                "strokeType": "BASIC"
              }
            },
            {
              "id": "253:206",
              "name": "Group",
              "type": "GROUP",
              "scrollBehavior": "SCROLLS",
              "children": [
                {
                  "id": "253:207",
                  "name": "Vector",
                  "type": "VECTOR",
                  "scrollBehavior": "SCROLLS",
                  "blendMode": "PASS_THROUGH",
                  "fills": [
                    {
                      "blendMode": "NORMAL",
                      "type": "SOLID",
                      "color": {
                        "r": 0.45490196347236633,
                        "g": 0.5411764979362488,
                        "b": 0.6470588445663452,
                        "a": 1
                      }
                    }
                  ],
                  "strokes": [],
                  "strokeWeight": 21.33333396911621,
                  "strokeAlign": "INSIDE",
                  "absoluteBoundingBox": {
                    "x": 36,
                    "y": 3850.303955078125,
                    "width": 8.69500732421875,
                    "height": 8.696001052856445
                  },
                  "absoluteRenderBounds": {
                    "x": 36,
                    "y": 3850.303955078125,
                    "width": 8.69500732421875,
                    "height": 8.696044921875
                  },
                  "constraints": {
                    "vertical": "SCALE",
                    "horizontal": "SCALE"
                  },
                  "effects": [],
                  "interactions": [],
                  "complexStrokeProperties": {
                    "strokeType": "BASIC"
                  }
                }
              ],
              "blendMode": "PASS_THROUGH",
              "clipsContent": false,
              "background": [],
              "fills": [],
              "strokes": [],
              "strokeWeight": 21.33333396911621,
              "strokeAlign": "INSIDE",
              "backgroundColor": {
                "r": 0,
                "g": 0,
                "b": 0,
                "a": 0
              },
              "absoluteBoundingBox": {
                "x": 36,
                "y": 3850.303955078125,
                "width": 8.69500732421875,
                "height": 8.696001052856445
              },
              "absoluteRenderBounds": {
                "x": 36,
                "y": 3850.303955078125,
                "width": 8.69500732421875,
                "height": 8.696044921875
              },
              "constraints": {
                "vertical": "SCALE",
                "horizontal": "SCALE"
              },
              "effects": [],
              "interactions": [],
              "complexStrokeProperties": {
                "strokeType": "BASIC"
              }
            },
            {
              "id": "253:208",
              "name": "Group",
              "type": "GROUP",
              "scrollBehavior": "SCROLLS",
              "children": [
                {
                  "id": "253:209",
                  "name": "Vector",
                  "type": "VECTOR",
                  "scrollBehavior": "SCROLLS",
                  "blendMode": "PASS_THROUGH",
                  "fills": [
                    {
                      "blendMode": "NORMAL",
                      "type": "SOLID",
                      "color": {
                        "r": 0.45490196347236633,
                        "g": 0.5411764979362488,
                        "b": 0.6470588445663452,
                        "a": 1
                      }
                    }
                  ],
                  "strokes": [],
                  "strokeWeight": 21.33333396911621,
                  "strokeAlign": "INSIDE",
                  "absoluteBoundingBox": {
                    "x": 39.5,
                    "y": 3838.5,
                    "width": 6.977993011474609,
                    "height": 7.658992767333984
                  },
                  "absoluteRenderBounds": {
                    "x": 39.5,
                    "y": 3838.5,
                    "width": 6.977993011474609,
                    "height": 7.658935546875
                  },
                  "constraints": {
                    "vertical": "SCALE",
                    "horizontal": "SCALE"
                  },
                  "effects": [],
                  "interactions": [],
                  "complexStrokeProperties": {
                    "strokeType": "BASIC"
                  }
                }
              ],
              "blendMode": "PASS_THROUGH",
              "clipsContent": false,
              "background": [],
              "fills": [],
              "strokes": [],
              "strokeWeight": 21.33333396911621,
              "strokeAlign": "INSIDE",
              "backgroundColor": {
                "r": 0,
                "g": 0,
                "b": 0,
                "a": 0
              },
              "absoluteBoundingBox": {
                "x": 39.5,
                "y": 3838.5,
                "width": 6.977993011474609,
                "height": 7.658992767333984
              },
              "absoluteRenderBounds": {
                "x": 39.5,
                "y": 3838.5,
                "width": 6.977993011474609,
                "height": 7.658992767333984
              },
              "constraints": {
                "vertical": "SCALE",
                "horizontal": "SCALE"
              },
              "effects": [],
              "interactions": [],
              "complexStrokeProperties": {
                "strokeType": "BASIC"
              }
            },
            {
              "id": "253:210",
              "name": "Group",
              "type": "GROUP",
              "scrollBehavior": "SCROLLS",
              "children": [
                {
                  "id": "253:211",
                  "name": "Vector",
                  "type": "VECTOR",
                  "scrollBehavior": "SCROLLS",
                  "blendMode": "PASS_THROUGH",
                  "fills": [
                    {
                      "blendMode": "NORMAL",
                      "type": "SOLID",
                      "color": {
                        "r": 0.45490196347236633,
                        "g": 0.5411764979362488,
                        "b": 0.6470588445663452,
                        "a": 1
                      }
                    }
                  ],
                  "strokes": [],
                  "strokeWeight": 21.33333396911621,
                  "strokeAlign": "INSIDE",
                  "absoluteBoundingBox": {
                    "x": 49.75,
                    "y": 3848.5,
                    "width": 6.75,
                    "height": 7
                  },
                  "absoluteRenderBounds": {
                    "x": 49.75,
                    "y": 3848.5,
                    "width": 6.75,
                    "height": 7
                  },
                  "constraints": {
                    "vertical": "SCALE",
                    "horizontal": "SCALE"
                  },
                  "effects": [],
                  "interactions": [],
                  "complexStrokeProperties": {
                    "strokeType": "BASIC"
                  }
                }
              ],
              "blendMode": "PASS_THROUGH",
              "clipsContent": false,
              "background": [],
              "fills": [],
              "strokes": [],
              "strokeWeight": 21.33333396911621,
              "strokeAlign": "INSIDE",
              "backgroundColor": {
                "r": 0,
                "g": 0,
                "b": 0,
                "a": 0
              },
              "absoluteBoundingBox": {
                "x": 49.75,
                "y": 3848.5,
                "width": 6.75,
                "height": 7
              },
              "absoluteRenderBounds": {
                "x": 49.75,
                "y": 3848.5,
                "width": 6.75,
                "height": 7
              },
              "constraints": {
                "vertical": "SCALE",
                "horizontal": "SCALE"
              },
              "effects": [],
              "interactions": [],
              "complexStrokeProperties": {
                "strokeType": "BASIC"
              }
            },
            {
              "id": "253:212",
              "name": "Group",
              "type": "GROUP",
              "scrollBehavior": "SCROLLS",
              "children": [
                {
                  "id": "253:213",
                  "name": "Vector",
                  "type": "VECTOR",
                  "scrollBehavior": "SCROLLS",
                  "blendMode": "PASS_THROUGH",
                  "fills": [
                    {
                      "blendMode": "NORMAL",
                      "type": "SOLID",
                      "color": {
                        "r": 0.45490196347236633,
                        "g": 0.5411764979362488,
                        "b": 0.6470588445663452,
                        "a": 1
                      }
                    }
                  ],
                  "strokes": [],
                  "strokeWeight": 21.33333396911621,
                  "strokeAlign": "INSIDE",
                  "absoluteBoundingBox": {
                    "x": 50.409000396728516,
                    "y": 3838.5,
                    "width": 6.091014862060547,
                    "height": 6.090991973876953
                  },
                  "absoluteRenderBounds": {
                    "x": 50.409000396728516,
                    "y": 3838.5,
                    "width": 6.091014862060547,
                    "height": 6.091064453125
                  },
                  "constraints": {
                    "vertical": "SCALE",
                    "horizontal": "SCALE"
                  },
                  "effects": [],
                  "interactions": [],
                  "complexStrokeProperties": {
                    "strokeType": "BASIC"
                  }
                }
              ],
              "blendMode": "PASS_THROUGH",
              "clipsContent": false,
              "background": [],
              "fills": [],
              "strokes": [],
              "strokeWeight": 21.33333396911621,
              "strokeAlign": "INSIDE",
              "backgroundColor": {
                "r": 0,
                "g": 0,
                "b": 0,
                "a": 0
              },
              "absoluteBoundingBox": {
                "x": 50.409000396728516,
                "y": 3838.5,
                "width": 6.091014862060547,
                "height": 6.090991973876953
              },
              "absoluteRenderBounds": {
                "x": 50.409000396728516,
                "y": 3838.5,
                "width": 6.091014862060547,
                "height": 6.091064453125
              },
              "constraints": {
                "vertical": "SCALE",
                "horizontal": "SCALE"
              },
              "effects": [],
              "interactions": [],
              "complexStrokeProperties": {
                "strokeType": "BASIC"
              }
            },
            {
              "id": "253:214",
              "name": "Group",
              "type": "GROUP",
              "scrollBehavior": "SCROLLS",
              "children": [
                {
                  "id": "253:215",
                  "name": "Vector",
                  "type": "VECTOR",
                  "scrollBehavior": "SCROLLS",
                  "blendMode": "PASS_THROUGH",
                  "fills": [
                    {
                      "blendMode": "NORMAL",
                      "type": "SOLID",
                      "color": {
                        "r": 0.45490196347236633,
                        "g": 0.5411764979362488,
                        "b": 0.6470588445663452,
                        "a": 1
                      }
                    }
                  ],
                  "strokes": [],
                  "strokeWeight": 21.33333396911621,
                  "strokeAlign": "INSIDE",
                  "absoluteBoundingBox": {
                    "x": 39.5,
                    "y": 3839.408935546875,
                    "width": 9.97799301147461,
                    "height": 9.726991653442383
                  },
                  "absoluteRenderBounds": {
                    "x": 39.5,
                    "y": 3839.408935546875,
                    "width": 9.97799301147461,
                    "height": 9.72705078125
                  },
                  "constraints": {
                    "vertical": "SCALE",
                    "horizontal": "SCALE"
                  },
                  "effects": [],
                  "interactions": [],
                  "complexStrokeProperties": {
                    "strokeType": "BASIC"
                  }
                }
              ],
              "blendMode": "PASS_THROUGH",
              "clipsContent": false,
              "background": [],
              "fills": [],
              "strokes": [],
              "strokeWeight": 21.33333396911621,
              "strokeAlign": "INSIDE",
              "backgroundColor": {
                "r": 0,
                "g": 0,
                "b": 0,
                "a": 0
              },
              "absoluteBoundingBox": {
                "x": 39.5,
                "y": 3839.408935546875,
                "width": 9.97799301147461,
                "height": 9.726991653442383
              },
              "absoluteRenderBounds": {
                "x": 39.5,
                "y": 3839.408935546875,
                "width": 9.97799301147461,
                "height": 9.72705078125
              },
              "constraints": {
                "vertical": "SCALE",
                "horizontal": "SCALE"
              },
              "effects": [],
              "interactions": [],
              "complexStrokeProperties": {
                "strokeType": "BASIC"
              }
            },
            {
              "id": "253:216",
              "name": "Group",
              "type": "GROUP",
              "scrollBehavior": "SCROLLS",
              "children": [
                {
                  "id": "253:217",
                  "name": "Vector",
                  "type": "VECTOR",
                  "scrollBehavior": "SCROLLS",
                  "blendMode": "PASS_THROUGH",
                  "fills": [
                    {
                      "blendMode": "NORMAL",
                      "type": "SOLID",
                      "color": {
                        "r": 0.45490196347236633,
                        "g": 0.5411764979362488,
                        "b": 0.6470588445663452,
                        "a": 1
                      }
                    }
                  ],
                  "strokes": [],
                  "strokeWeight": 21.33333396911621,
                  "strokeAlign": "INSIDE",
                  "absoluteBoundingBox": {
                    "x": 50.25,
                    "y": 3845.52294921875,
                    "width": 6.4999847412109375,
                    "height": 3.362985610961914
                  },
                  "absoluteRenderBounds": {
                    "x": 50.25,
                    "y": 3845.52294921875,
                    "width": 6.4999847412109375,
                    "height": 3.363037109375
                  },
                  "constraints": {
                    "vertical": "SCALE",
                    "horizontal": "SCALE"
                  },
                  "effects": [],
                  "interactions": [],
                  "complexStrokeProperties": {
                    "strokeType": "BASIC"
                  }
                }
              ],
              "blendMode": "PASS_THROUGH",
              "clipsContent": false,
              "background": [],
              "fills": [],
              "strokes": [],
              "strokeWeight": 21.33333396911621,
              "strokeAlign": "INSIDE",
              "backgroundColor": {
                "r": 0,
                "g": 0,
                "b": 0,
                "a": 0
              },
              "absoluteBoundingBox": {
                "x": 50.25,
                "y": 3845.52294921875,
                "width": 6.4999847412109375,
                "height": 3.362985610961914
              },
              "absoluteRenderBounds": {
                "x": 50.25,
                "y": 3845.52294921875,
                "width": 6.4999847412109375,
                "height": 3.363037109375
              },
              "constraints": {
                "vertical": "SCALE",
                "horizontal": "SCALE"
              },
              "effects": [],
              "interactions": [],
              "complexStrokeProperties": {
                "strokeType": "BASIC"
              }
            },
            {
              "id": "253:218",
              "name": "Group",
              "type": "GROUP",
              "scrollBehavior": "SCROLLS",
              "children": [
                {
                  "id": "253:219",
                  "name": "Vector",
                  "type": "VECTOR",
                  "scrollBehavior": "SCROLLS",
                  "blendMode": "PASS_THROUGH",
                  "fills": [
                    {
                      "blendMode": "NORMAL",
                      "type": "SOLID",
                      "color": {
                        "r": 0.45490196347236633,
                        "g": 0.5411764979362488,
                        "b": 0.6470588445663452,
                        "a": 1
                      }
                    }
                  ],
                  "strokes": [],
                  "strokeWeight": 21.33333396911621,
                  "strokeAlign": "INSIDE",
                  "absoluteBoundingBox": {
                    "x": 47.02199935913086,
                    "y": 3849.928955078125,
                    "width": 1.9999961853027344,
                    "height": 4.271993637084961
                  },
                  "absoluteRenderBounds": {
                    "x": 47.02199935913086,
                    "y": 3849.928955078125,
                    "width": 1.9999961853027344,
                    "height": 4.27197265625
                  },
                  "constraints": {
                    "vertical": "SCALE",
                    "horizontal": "SCALE"
                  },
                  "effects": [],
                  "interactions": [],
                  "complexStrokeProperties": {
                    "strokeType": "BASIC"
                  }
                }
              ],
              "blendMode": "PASS_THROUGH",
              "clipsContent": false,
              "background": [],
              "fills": [],
              "strokes": [],
              "strokeWeight": 21.33333396911621,
              "strokeAlign": "INSIDE",
              "backgroundColor": {
                "r": 0,
                "g": 0,
                "b": 0,
                "a": 0
              },
              "absoluteBoundingBox": {
                "x": 47.02199935913086,
                "y": 3849.928955078125,
                "width": 1.9999961853027344,
                "height": 4.271993637084961
              },
              "absoluteRenderBounds": {
                "x": 47.02199935913086,
                "y": 3849.928955078125,
                "width": 1.9999961853027344,
                "height": 4.271993637084961
              },
              "constraints": {
                "vertical": "SCALE",
                "horizontal": "SCALE"
              },
              "effects": [],
              "interactions": [],
              "complexStrokeProperties": {
                "strokeType": "BASIC"
              }
            },
            {
              "id": "253:220",
              "name": "Group",
              "type": "GROUP",
              "scrollBehavior": "SCROLLS",
              "children": [
                {
                  "id": "253:221",
                  "name": "Vector",
                  "type": "VECTOR",
                  "scrollBehavior": "SCROLLS",
                  "blendMode": "PASS_THROUGH",
                  "fills": [
                    {
                      "blendMode": "NORMAL",
                      "type": "SOLID",
                      "color": {
                        "r": 0.45490196347236633,
                        "g": 0.5411764979362488,
                        "b": 0.6470588445663452,
                        "a": 1
                      }
                    }
                  ],
                  "strokes": [],
                  "strokeWeight": 21.33333396911621,
                  "strokeAlign": "INSIDE",
                  "absoluteBoundingBox": {
                    "x": 39.5,
                    "y": 3849.864013671875,
                    "width": 6.750007629394531,
                    "height": 5.636014938354492
                  },
                  "absoluteRenderBounds": {
                    "x": 39.5,
                    "y": 3849.864013671875,
                    "width": 6.750007629394531,
                    "height": 5.635986328125
                  },
                  "constraints": {
                    "vertical": "SCALE",
                    "horizontal": "SCALE"
                  },
                  "effects": [],
                  "interactions": [],
                  "complexStrokeProperties": {
                    "strokeType": "BASIC"
                  }
                }
              ],
              "blendMode": "PASS_THROUGH",
              "clipsContent": false,
              "background": [],
              "fills": [],
              "strokes": [],
              "strokeWeight": 21.33333396911621,
              "strokeAlign": "INSIDE",
              "backgroundColor": {
                "r": 0,
                "g": 0,
                "b": 0,
                "a": 0
              },
              "absoluteBoundingBox": {
                "x": 39.5,
                "y": 3849.864013671875,
                "width": 6.750007629394531,
                "height": 5.636014938354492
              },
              "absoluteRenderBounds": {
                "x": 39.5,
                "y": 3849.864013671875,
                "width": 6.750007629394531,
                "height": 5.636014938354492
              },
              "constraints": {
                "vertical": "SCALE",
                "horizontal": "SCALE"
              },
              "effects": [],
              "interactions": [],
              "complexStrokeProperties": {
                "strokeType": "BASIC"
              }
            }
          ],
          "blendMode": "PASS_THROUGH",
          "clipsContent": true,
          "background": [
            {
              "blendMode": "NORMAL",
              "visible": false,
              "type": "SOLID",
              "color": {
                "r": 1,
                "g": 1,
                "b": 1,
                "a": 1
              }
            }
          ],
          "fills": [
            {
              "blendMode": "NORMAL",
              "visible": false,
              "type": "SOLID",
              "color": {
                "r": 1,
                "g": 1,
                "b": 1,
                "a": 1
              }
            }
          ],
          "strokes": [],
          "strokeWeight": 1,
          "strokeAlign": "INSIDE",
          "backgroundColor": {
            "r": 0,
            "g": 0,
            "b": 0,
            "a": 0
          },
          "absoluteBoundingBox": {
            "x": 36,
            "y": 3835,
            "width": 24,
            "height": 24
          },
          "absoluteRenderBounds": {
            "x": 36,
            "y": 3835,
            "width": 24,
            "height": 24
          },
          "constraints": {
            "vertical": "SCALE",
            "horizontal": "SCALE"
          },
          "effects": [],
          "interactions": [],
          "complexStrokeProperties": {
            "strokeType": "BASIC"
          }
        },
        {
          "id": "253:247",
          "name": "line",
          "type": "RECTANGLE",
          "scrollBehavior": "SCROLLS",
          "blendMode": "PASS_THROUGH",
          "fills": [
            {
              "blendMode": "NORMAL",
              "type": "SOLID",
              "color": {
                "r": 0.45490196347236633,
                "g": 0.5411764979362488,
                "b": 0.6470588445663452,
                "a": 1
              }
            }
          ],
          "strokes": [],
          "strokeWeight": 1,
          "strokeAlign": "INSIDE",
          "cornerRadius": 15,
          "cornerSmoothing": 0,
          "absoluteBoundingBox": {
            "x": 74,
            "y": 3856,
            "width": 66,
            "height": 3
          },
          "absoluteRenderBounds": {
            "x": 74,
            "y": 3856,
            "width": 66,
            "height": 3
          },
          "constraints": {
            "vertical": "TOP",
            "horizontal": "LEFT"
          },
          "effects": [],
          "interactions": [],
          "complexStrokeProperties": {
            "strokeType": "BASIC"
          }
        },
        {
          "id": "253:248",
          "name": "QRCode",
          "type": "TEXT",
          "scrollBehavior": "SCROLLS",
          "blendMode": "PASS_THROUGH",
          "fills": [
            {
              "blendMode": "NORMAL",
              "type": "SOLID",
              "color": {
                "r": 0.45490196347236633,
                "g": 0.5411764979362488,
                "b": 0.6470588445663452,
                "a": 1
              }
            }
          ],
          "strokes": [],
          "strokeWeight": 1,
          "strokeAlign": "OUTSIDE",
          "absoluteBoundingBox": {
            "x": 74,
            "y": 3835,
            "width": 65,
            "height": 16
          },
          "absoluteRenderBounds": {
            "x": 78.1328125,
            "y": 3836,
            "width": 56.984375,
            "height": 13.9765625
          },
          "constraints": {
            "vertical": "TOP",
            "horizontal": "LEFT"
          },
          "characters": "QRCode",
          "characterStyleOverrides": [],
          "styleOverrideTable": {},
          "lineTypes": [
            "NONE"
          ],
          "lineIndentations": [
            0
          ],
          "style": {
            "fontFamily": "Roboto",
            "fontPostScriptName": "Roboto-Medium",
            "fontStyle": "Medium",
            "fontWeight": 500,
            "fontSize": 16,
            "textAlignHorizontal": "CENTER",
            "textAlignVertical": "CENTER",
            "letterSpacing": 0,
            "lineHeightPx": 18.75,
            "lineHeightPercent": 100,
            "lineHeightUnit": "INTRINSIC_%"
          },
          "layoutVersion": 3,
          "effects": [],
          "interactions": [],
          "complexStrokeProperties": {
            "strokeType": "BASIC"
          }
        },
        {
          "id": "253:222",
          "name": "ic-map",
          "type": "FRAME",
          "scrollBehavior": "SCROLLS",
          "children": [
            {
              "id": "253:223",
              "name": "Group",
              "type": "GROUP",
              "scrollBehavior": "SCROLLS",
              "children": [
                {
                  "id": "253:224",
                  "name": "Group",
                  "type": "GROUP",
                  "scrollBehavior": "SCROLLS",
                  "children": [
                    {
                      "id": "253:225",
                      "name": "Group",
                      "type": "GROUP",
                      "scrollBehavior": "SCROLLS",
                      "children": [
                        {
                          "id": "253:226",
                          "name": "Vector",
                          "type": "VECTOR",
                          "scrollBehavior": "SCROLLS",
                          "blendMode": "PASS_THROUGH",
                          "fills": [
                            {
                              "blendMode": "NORMAL",
                              "type": "SOLID",
                              "color": {
                                "r": 0.8823529481887817,
                                "g": 0.8901960849761963,
                                "b": 0.9019607901573181,
                                "a": 1
                              }
                            }
                          ],
                          "strokes": [],
                          "strokeWeight": 1,
                          "strokeAlign": "INSIDE",
                          "absoluteBoundingBox": {
                            "x": 253.5,
                            "y": 3835,
                            "width": 10.5,
                            "height": 13.5
                          },
                          "absoluteRenderBounds": {
                            "x": 253.5,
                            "y": 3835,
                            "width": 10.5,
                            "height": 13.5
                          },
                          "constraints": {
                            "vertical": "SCALE",
                            "horizontal": "SCALE"
                          },
                          "effects": [],
                          "interactions": [],
                          "complexStrokeProperties": {
                            "strokeType": "BASIC"
                          }
                        }
                      ],
                      "blendMode": "PASS_THROUGH",
                      "clipsContent": false,
                      "background": [],
                      "fills": [],
                      "strokes": [],
                      "strokeWeight": 1,
                      "strokeAlign": "INSIDE",
                      "backgroundColor": {
                        "r": 0,
                        "g": 0,
                        "b": 0,
                        "a": 0
                      },
                      "absoluteBoundingBox": {
                        "x": 253.5,
                        "y": 3835,
                        "width": 10.5,
                        "height": 13.5
                      },
                      "absoluteRenderBounds": {
                        "x": 253.5,
                        "y": 3835,
                        "width": 10.5,
                        "height": 13.5
                      },
                      "constraints": {
                        "vertical": "SCALE",
                        "horizontal": "SCALE"
                      },
                      "effects": [],
                      "interactions": [],
                      "complexStrokeProperties": {
                        "strokeType": "BASIC"
                      }
                    }
                  ],
                  "blendMode": "PASS_THROUGH",
                  "clipsContent": false,
                  "background": [],
                  "fills": [],
                  "strokes": [],
                  "strokeWeight": 1,
                  "strokeAlign": "INSIDE",
                  "backgroundColor": {
                    "r": 0,
                    "g": 0,
                    "b": 0,
                    "a": 0
                  },
                  "absoluteBoundingBox": {
                    "x": 253.5,
                    "y": 3835,
                    "width": 10.5,
                    "height": 13.5
                  },
                  "absoluteRenderBounds": {
                    "x": 253.5,
                    "y": 3835,
                    "width": 10.5,
                    "height": 13.5
                  },
                  "constraints": {
                    "vertical": "SCALE",
                    "horizontal": "SCALE"
                  },
                  "effects": [],
                  "interactions": [],
                  "complexStrokeProperties": {
                    "strokeType": "BASIC"
                  }
                },
                {
                  "id": "253:227",
                  "name": "Group",
                  "type": "GROUP",
                  "scrollBehavior": "SCROLLS",
                  "children": [
                    {
                      "id": "253:228",
                      "name": "Group",
                      "type": "GROUP",
                      "scrollBehavior": "SCROLLS",
                      "children": [
                        {
                          "id": "253:229",
                          "name": "Vector",
                          "type": "VECTOR",
                          "scrollBehavior": "SCROLLS",
                          "blendMode": "PASS_THROUGH",
                          "fills": [
                            {
                              "blendMode": "NORMAL",
                              "type": "SOLID",
                              "color": {
                                "r": 0.8823529481887817,
                                "g": 0.8901960849761963,
                                "b": 0.9019607901573181,
                                "a": 1
                              }
                            }
                          ],
                          "strokes": [],
                          "strokeWeight": 1,
                          "strokeAlign": "INSIDE",
                          "absoluteBoundingBox": {
                            "x": 240,
                            "y": 3841,
                            "width": 7.5,
                            "height": 18
                          },
                          "absoluteRenderBounds": {
                            "x": 240,
                            "y": 3841,
                            "width": 7.5,
                            "height": 18
                          },
                          "constraints": {
                            "vertical": "SCALE",
                            "horizontal": "SCALE"
                          },
                          "effects": [],
                          "interactions": [],
                          "complexStrokeProperties": {
                            "strokeType": "BASIC"
                          }
                        }
                      ],
                      "blendMode": "PASS_THROUGH",
                      "clipsContent": false,
                      "background": [],
                      "fills": [],
                      "strokes": [],
                      "strokeWeight": 1,
                      "strokeAlign": "INSIDE",
                      "backgroundColor": {
                        "r": 0,
                        "g": 0,
                        "b": 0,
                        "a": 0
                      },
                      "absoluteBoundingBox": {
                        "x": 240,
                        "y": 3841,
                        "width": 7.5,
                        "height": 18
                      },
                      "absoluteRenderBounds": {
                        "x": 240,
                        "y": 3841,
                        "width": 7.5,
                        "height": 18
                      },
                      "constraints": {
                        "vertical": "SCALE",
                        "horizontal": "SCALE"
                      },
                      "effects": [],
                      "interactions": [],
                      "complexStrokeProperties": {
                        "strokeType": "BASIC"
                      }
                    }
                  ],
                  "blendMode": "PASS_THROUGH",
                  "clipsContent": false,
                  "background": [],
                  "fills": [],
                  "strokes": [],
                  "strokeWeight": 1,
                  "strokeAlign": "INSIDE",
                  "backgroundColor": {
                    "r": 0,
                    "g": 0,
                    "b": 0,
                    "a": 0
                  },
                  "absoluteBoundingBox": {
                    "x": 240,
                    "y": 3841,
                    "width": 7.5,
                    "height": 18
                  },
                  "absoluteRenderBounds": {
                    "x": 240,
                    "y": 3841,
                    "width": 7.5,
                    "height": 18
                  },
                  "constraints": {
                    "vertical": "SCALE",
                    "horizontal": "SCALE"
                  },
                  "effects": [],
                  "interactions": [],
                  "complexStrokeProperties": {
                    "strokeType": "BASIC"
                  }
                },
                {
                  "id": "253:230",
                  "name": "Group",
                  "type": "GROUP",
                  "scrollBehavior": "SCROLLS",
                  "children": [
                    {
                      "id": "253:231",
                      "name": "Group",
                      "type": "GROUP",
                      "scrollBehavior": "SCROLLS",
                      "children": [
                        {
                          "id": "253:232",
                          "name": "Vector",
                          "type": "VECTOR",
                          "scrollBehavior": "SCROLLS",
                          "blendMode": "PASS_THROUGH",
                          "fills": [
                            {
                              "blendMode": "NORMAL",
                              "type": "SOLID",
                              "color": {
                                "r": 0.8823529481887817,
                                "g": 0.8901960849761963,
                                "b": 0.9019607901573181,
                                "a": 1
                              }
                            }
                          ],
                          "strokes": [],
                          "strokeWeight": 1,
                          "strokeAlign": "INSIDE",
                          "absoluteBoundingBox": {
                            "x": 256.5,
                            "y": 3844.466552734375,
                            "width": 7.5,
                            "height": 14.53350830078125
                          },
                          "absoluteRenderBounds": {
                            "x": 256.5,
                            "y": 3844.466552734375,
                            "width": 7.5,
                            "height": 14.533447265625
                          },
                          "constraints": {
                            "vertical": "SCALE",
                            "horizontal": "SCALE"
                          },
                          "effects": [],
                          "interactions": [],
                          "complexStrokeProperties": {
                            "strokeType": "BASIC"
                          }
                        }
                      ],
                      "blendMode": "PASS_THROUGH",
                      "clipsContent": false,
                      "background": [],
                      "fills": [],
                      "strokes": [],
                      "strokeWeight": 1,
                      "strokeAlign": "INSIDE",
                      "backgroundColor": {
                        "r": 0,
                        "g": 0,
                        "b": 0,
                        "a": 0
                      },
                      "absoluteBoundingBox": {
                        "x": 256.5,
                        "y": 3844.466552734375,
                        "width": 7.5,
                        "height": 14.53350830078125
                      },
                      "absoluteRenderBounds": {
                        "x": 256.5,
                        "y": 3844.466552734375,
                        "width": 7.5,
                        "height": 14.533447265625
                      },
                      "constraints": {
                        "vertical": "SCALE",
                        "horizontal": "SCALE"
                      },
                      "effects": [],
                      "interactions": [],
                      "complexStrokeProperties": {
                        "strokeType": "BASIC"
                      }
                    }
                  ],
                  "blendMode": "PASS_THROUGH",
                  "clipsContent": false,
                  "background": [],
                  "fills": [],
                  "strokes": [],
                  "strokeWeight": 1,
                  "strokeAlign": "INSIDE",
                  "backgroundColor": {
                    "r": 0,
                    "g": 0,
                    "b": 0,
                    "a": 0
                  },
                  "absoluteBoundingBox": {
                    "x": 256.5,
                    "y": 3844.466552734375,
                    "width": 7.5,
                    "height": 14.53350830078125
                  },
                  "absoluteRenderBounds": {
                    "x": 256.5,
                    "y": 3844.466552734375,
                    "width": 7.5,
                    "height": 14.533447265625
                  },
                  "constraints": {
                    "vertical": "SCALE",
                    "horizontal": "SCALE"
                  },
                  "effects": [],
                  "interactions": [],
                  "complexStrokeProperties": {
                    "strokeType": "BASIC"
                  }
                },
                {
                  "id": "253:233",
                  "name": "Group",
                  "type": "GROUP",
                  "scrollBehavior": "SCROLLS",
                  "children": [
                    {
                      "id": "253:234",
                      "name": "Group",
                      "type": "GROUP",
                      "scrollBehavior": "SCROLLS",
                      "children": [
                        {
                          "id": "253:235",
                          "name": "Vector",
                          "type": "VECTOR",
                          "scrollBehavior": "SCROLLS",
                          "blendMode": "PASS_THROUGH",
                          "fills": [
                            {
                              "blendMode": "NORMAL",
                              "type": "SOLID",
                              "color": {
                                "r": 0.8823529481887817,
                                "g": 0.8901960849761963,
                                "b": 0.9019607901573181,
                                "a": 1
                              }
                            }
                          ],
                          "strokes": [],
                          "strokeWeight": 1,
                          "strokeAlign": "INSIDE",
                          "absoluteBoundingBox": {
                            "x": 249,
                            "y": 3841,
                            "width": 6,
                            "height": 17.756999969482422
                          },
                          "absoluteRenderBounds": {
                            "x": 249,
                            "y": 3841,
                            "width": 6,
                            "height": 17.757080078125
                          },
                          "constraints": {
                            "vertical": "SCALE",
                            "horizontal": "SCALE"
                          },
                          "effects": [],
                          "interactions": [],
                          "complexStrokeProperties": {
                            "strokeType": "BASIC"
                          }
                        }
                      ],
                      "blendMode": "PASS_THROUGH",
                      "clipsContent": false,
                      "background": [],
                      "fills": [],
                      "strokes": [],
                      "strokeWeight": 1,
                      "strokeAlign": "INSIDE",
                      "backgroundColor": {
                        "r": 0,
                        "g": 0,
                        "b": 0,
                        "a": 0
                      },
                      "absoluteBoundingBox": {
                        "x": 249,
                        "y": 3841,
                        "width": 6,
                        "height": 17.756999969482422
                      },
                      "absoluteRenderBounds": {
                        "x": 249,
                        "y": 3841,
                        "width": 6,
                        "height": 17.757080078125
                      },
                      "constraints": {
                        "vertical": "SCALE",
                        "horizontal": "SCALE"
                      },
                      "effects": [],
                      "interactions": [],
                      "complexStrokeProperties": {
                        "strokeType": "BASIC"
                      }
                    }
                  ],
                  "blendMode": "PASS_THROUGH",
                  "clipsContent": false,
                  "background": [],
                  "fills": [],
                  "strokes": [],
                  "strokeWeight": 1,
                  "strokeAlign": "INSIDE",
                  "backgroundColor": {
                    "r": 0,
                    "g": 0,
                    "b": 0,
                    "a": 0
                  },
                  "absoluteBoundingBox": {
                    "x": 249,
                    "y": 3841,
                    "width": 6,
                    "height": 17.756999969482422
                  },
                  "absoluteRenderBounds": {
                    "x": 249,
                    "y": 3841,
                    "width": 6,
                    "height": 17.757080078125
                  },
                  "constraints": {
                    "vertical": "SCALE",
                    "horizontal": "SCALE"
                  },
                  "effects": [],
                  "interactions": [],
                  "complexStrokeProperties": {
                    "strokeType": "BASIC"
                  }
                }
              ],
              "blendMode": "PASS_THROUGH",
              "clipsContent": false,
              "background": [],
              "fills": [],
              "strokes": [],
              "strokeWeight": 1,
              "strokeAlign": "INSIDE",
              "backgroundColor": {
                "r": 0,
                "g": 0,
                "b": 0,
                "a": 0
              },
              "absoluteBoundingBox": {
                "x": 240,
                "y": 3835,
                "width": 24,
                "height": 24
              },
              "absoluteRenderBounds": {
                "x": 240,
                "y": 3835,
                "width": 24,
                "height": 24
              },
              "constraints": {
                "vertical": "SCALE",
                "horizontal": "SCALE"
              },
              "effects": [],
              "interactions": [],
              "complexStrokeProperties": {
                "strokeType": "BASIC"
              }
            }
          ],
          "blendMode": "PASS_THROUGH",
          "clipsContent": true,
          "background": [
            {
              "blendMode": "NORMAL",
              "visible": false,
              "type": "SOLID",
              "color": {
                "r": 1,
                "g": 1,
                "b": 1,
                "a": 1
              }
            }
          ],
          "fills": [
            {
              "blendMode": "NORMAL",
              "visible": false,
              "type": "SOLID",
              "color": {
                "r": 1,
                "g": 1,
                "b": 1,
                "a": 1
              }
            }
          ],
          "strokes": [],
          "strokeWeight": 1,
          "strokeAlign": "INSIDE",
          "backgroundColor": {
            "r": 0,
            "g": 0,
            "b": 0,
            "a": 0
          },
          "absoluteBoundingBox": {
            "x": 240,
            "y": 3835,
            "width": 24,
            "height": 24
          },
          "absoluteRenderBounds": {
            "x": 240,
            "y": 3835,
            "width": 24,
            "height": 24
          },
          "constraints": {
            "vertical": "TOP",
            "horizontal": "LEFT"
          },
          "effects": [],
          "interactions": [],
          "complexStrokeProperties": {
            "strokeType": "BASIC"
          }
        },
        {
          "id": "253:236",
          "name": "ic-noti",
          "type": "FRAME",
          "scrollBehavior": "SCROLLS",
          "children": [
            {
              "id": "253:237",
              "name": "Group",
              "type": "GROUP",
              "scrollBehavior": "SCROLLS",
              "children": [
                {
                  "id": "253:238",
                  "name": "Group",
                  "type": "GROUP",
                  "scrollBehavior": "SCROLLS",
                  "children": [
                    {
                      "id": "253:239",
                      "name": "Vector",
                      "type": "VECTOR",
                      "scrollBehavior": "SCROLLS",
                      "blendMode": "PASS_THROUGH",
                      "fills": [
                        {
                          "blendMode": "NORMAL",
                          "type": "SOLID",
                          "color": {
                            "r": 0.8823529481887817,
                            "g": 0.8901960849761963,
                            "b": 0.9019607901573181,
                            "a": 1
                          }
                        }
                      ],
                      "strokes": [],
                      "strokeWeight": 21.33333396911621,
                      "strokeAlign": "INSIDE",
                      "absoluteBoundingBox": {
                        "x": 311.63177490234375,
                        "y": 3837.749755859375,
                        "width": 5.368265151977539,
                        "height": 10.13224983215332
                      },
                      "absoluteRenderBounds": {
                        "x": 311.63177490234375,
                        "y": 3837.749755859375,
                        "width": 5.368255615234375,
                        "height": 10.13232421875
                      },
                      "constraints": {
                        "vertical": "SCALE",
                        "horizontal": "SCALE"
                      },
                      "effects": [],
                      "interactions": [],
                      "complexStrokeProperties": {
                        "strokeType": "BASIC"
                      }
                    }
                  ],
                  "blendMode": "PASS_THROUGH",
                  "clipsContent": false,
                  "background": [],
                  "fills": [],
                  "strokes": [],
                  "strokeWeight": 21.33333396911621,
                  "strokeAlign": "INSIDE",
                  "backgroundColor": {
                    "r": 0,
                    "g": 0,
                    "b": 0,
                    "a": 0
                  },
                  "absoluteBoundingBox": {
                    "x": 311.63177490234375,
                    "y": 3837.749755859375,
                    "width": 5.368265151977539,
                    "height": 10.13224983215332
                  },
                  "absoluteRenderBounds": {
                    "x": 311.63177490234375,
                    "y": 3837.749755859375,
                    "width": 5.368265151977539,
                    "height": 10.13232421875
                  },
                  "constraints": {
                    "vertical": "SCALE",
                    "horizontal": "SCALE"
                  },
                  "effects": [],
                  "interactions": [],
                  "complexStrokeProperties": {
                    "strokeType": "BASIC"
                  }
                },
                {
                  "id": "253:240",
                  "name": "Group",
                  "type": "GROUP",
                  "scrollBehavior": "SCROLLS",
                  "children": [
                    {
                      "id": "253:241",
                      "name": "Vector",
                      "type": "VECTOR",
                      "scrollBehavior": "SCROLLS",
                      "blendMode": "PASS_THROUGH",
                      "fills": [
                        {
                          "blendMode": "NORMAL",
                          "type": "SOLID",
                          "color": {
                            "r": 0.8823529481887817,
                            "g": 0.8901960849761963,
                            "b": 0.9019607901573181,
                            "a": 1
                          }
                        }
                      ],
                      "strokes": [],
                      "strokeWeight": 21.33333396911621,
                      "strokeAlign": "INSIDE",
                      "absoluteBoundingBox": {
                        "x": 295,
                        "y": 3837.749755859375,
                        "width": 5.368255615234375,
                        "height": 10.13224983215332
                      },
                      "absoluteRenderBounds": {
                        "x": 295,
                        "y": 3837.749755859375,
                        "width": 5.368255615234375,
                        "height": 10.13232421875
                      },
                      "constraints": {
                        "vertical": "SCALE",
                        "horizontal": "SCALE"
                      },
                      "effects": [],
                      "interactions": [],
                      "complexStrokeProperties": {
                        "strokeType": "BASIC"
                      }
                    }
                  ],
                  "blendMode": "PASS_THROUGH",
                  "clipsContent": false,
                  "background": [],
                  "fills": [],
                  "strokes": [],
                  "strokeWeight": 21.33333396911621,
                  "strokeAlign": "INSIDE",
                  "backgroundColor": {
                    "r": 0,
                    "g": 0,
                    "b": 0,
                    "a": 0
                  },
                  "absoluteBoundingBox": {
                    "x": 295,
                    "y": 3837.749755859375,
                    "width": 5.368255615234375,
                    "height": 10.13224983215332
                  },
                  "absoluteRenderBounds": {
                    "x": 295,
                    "y": 3837.749755859375,
                    "width": 5.368255615234375,
                    "height": 10.13232421875
                  },
                  "constraints": {
                    "vertical": "SCALE",
                    "horizontal": "SCALE"
                  },
                  "effects": [],
                  "interactions": [],
                  "complexStrokeProperties": {
                    "strokeType": "BASIC"
                  }
                },
                {
                  "id": "253:242",
                  "name": "Group",
                  "type": "GROUP",
                  "scrollBehavior": "SCROLLS",
                  "children": [
                    {
                      "id": "253:243",
                      "name": "Vector",
                      "type": "VECTOR",
                      "scrollBehavior": "SCROLLS",
                      "blendMode": "PASS_THROUGH",
                      "fills": [
                        {
                          "blendMode": "NORMAL",
                          "type": "SOLID",
                          "color": {
                            "r": 0.8823529481887817,
                            "g": 0.8901960849761963,
                            "b": 0.9019607901573181,
                            "a": 1
                          }
                        }
                      ],
                      "strokes": [],
                      "strokeWeight": 21.33333396911621,
                      "strokeAlign": "INSIDE",
                      "absoluteBoundingBox": {
                        "x": 296,
                        "y": 3837,
                        "width": 20.000003814697266,
                        "height": 20
                      },
                      "absoluteRenderBounds": {
                        "x": 296,
                        "y": 3837,
                        "width": 20,
                        "height": 20
                      },
                      "constraints": {
                        "vertical": "SCALE",
                        "horizontal": "SCALE"
                      },
                      "effects": [],
                      "interactions": [],
                      "complexStrokeProperties": {
                        "strokeType": "BASIC"
                      }
                    },
                    {
                      "id": "253:244",
                      "name": "Vector",
                      "type": "VECTOR",
                      "scrollBehavior": "SCROLLS",
                      "blendMode": "PASS_THROUGH",
                      "fills": [
                        {
                          "blendMode": "NORMAL",
                          "type": "SOLID",
                          "color": {
                            "r": 0.8823529481887817,
                            "g": 0.8901960849761963,
                            "b": 0.9019607901573181,
                            "a": 1
                          }
                        }
                      ],
                      "strokes": [],
                      "strokeWeight": 21.33333396911621,
                      "strokeAlign": "INSIDE",
                      "absoluteBoundingBox": {
                        "x": 302.32598876953125,
                        "y": 3858,
                        "width": 7.347999572753906,
                        "height": 3
                      },
                      "absoluteRenderBounds": {
                        "x": 302.32598876953125,
                        "y": 3858,
                        "width": 7.347991943359375,
                        "height": 3
                      },
                      "constraints": {
                        "vertical": "SCALE",
                        "horizontal": "SCALE"
                      },
                      "effects": [],
                      "interactions": [],
                      "complexStrokeProperties": {
                        "strokeType": "BASIC"
                      }
                    }
                  ],
                  "blendMode": "PASS_THROUGH",
                  "clipsContent": false,
                  "background": [],
                  "fills": [],
                  "strokes": [],
                  "strokeWeight": 21.33333396911621,
                  "strokeAlign": "INSIDE",
                  "backgroundColor": {
                    "r": 0,
                    "g": 0,
                    "b": 0,
                    "a": 0
                  },
                  "absoluteBoundingBox": {
                    "x": 296,
                    "y": 3837,
                    "width": 20.000003814697266,
                    "height": 24
                  },
                  "absoluteRenderBounds": {
                    "x": 296,
                    "y": 3837,
                    "width": 20.000003814697266,
                    "height": 24
                  },
                  "constraints": {
                    "vertical": "SCALE",
                    "horizontal": "SCALE"
                  },
                  "effects": [],
                  "interactions": [],
                  "complexStrokeProperties": {
                    "strokeType": "BASIC"
                  }
                }
              ],
              "blendMode": "PASS_THROUGH",
              "clipsContent": false,
              "background": [],
              "fills": [],
              "strokes": [],
              "strokeWeight": 21.33333396911621,
              "strokeAlign": "INSIDE",
              "backgroundColor": {
                "r": 0,
                "g": 0,
                "b": 0,
                "a": 0
              },
              "absoluteBoundingBox": {
                "x": 295,
                "y": 3837,
                "width": 22.00001335144043,
                "height": 24
              },
              "absoluteRenderBounds": {
                "x": 295,
                "y": 3837,
                "width": 22.000030517578125,
                "height": 24
              },
              "constraints": {
                "vertical": "SCALE",
                "horizontal": "SCALE"
              },
              "effects": [],
              "interactions": [],
              "complexStrokeProperties": {
                "strokeType": "BASIC"
              }
            }
          ],
          "blendMode": "PASS_THROUGH",
          "clipsContent": true,
          "background": [
            {
              "blendMode": "NORMAL",
              "visible": false,
              "type": "SOLID",
              "color": {
                "r": 1,
                "g": 1,
                "b": 1,
                "a": 1
              }
            }
          ],
          "fills": [
            {
              "blendMode": "NORMAL",
              "visible": false,
              "type": "SOLID",
              "color": {
                "r": 1,
                "g": 1,
                "b": 1,
                "a": 1
              }
            }
          ],
          "strokes": [],
          "strokeWeight": 1,
          "strokeAlign": "INSIDE",
          "backgroundColor": {
            "r": 0,
            "g": 0,
            "b": 0,
            "a": 0
          },
          "absoluteBoundingBox": {
            "x": 294,
            "y": 3837,
            "width": 24,
            "height": 24
          },
          "absoluteRenderBounds": {
            "x": 294,
            "y": 3837,
            "width": 24,
            "height": 24
          },
          "constraints": {
            "vertical": "TOP",
            "horizontal": "LEFT"
          },
          "effects": [],
          "interactions": [],
          "complexStrokeProperties": {
            "strokeType": "BASIC"
          }
        },
        {
          "id": "253:245",
          "name": "ic-menu",
          "type": "FRAME",
          "scrollBehavior": "SCROLLS",
          "children": [
            {
              "id": "253:246",
              "name": "Vector",
              "type": "VECTOR",
              "scrollBehavior": "SCROLLS",
              "blendMode": "PASS_THROUGH",
              "fills": [
                {
                  "blendMode": "NORMAL",
                  "type": "SOLID",
                  "color": {
                    "r": 0.8823529481887817,
                    "g": 0.8901960849761963,
                    "b": 0.9019607901573181,
                    "a": 1
                  }
                }
              ],
              "strokes": [],
              "strokeWeight": 1,
              "strokeAlign": "INSIDE",
              "absoluteBoundingBox": {
                "x": 359,
                "y": 3836.68994140625,
                "width": 19.31999969482422,
                "height": 19.309999465942383
              },
              "absoluteRenderBounds": {
                "x": 359,
                "y": 3836.68994140625,
                "width": 19.32000732421875,
                "height": 19.31005859375
              },
              "constraints": {
                "vertical": "SCALE",
                "horizontal": "SCALE"
              },
              "effects": [],
              "interactions": [],
              "complexStrokeProperties": {
                "strokeType": "BASIC"
              }
            }
          ],
          "blendMode": "PASS_THROUGH",
          "clipsContent": true,
          "background": [
            {
              "blendMode": "NORMAL",
              "visible": false,
              "type": "SOLID",
              "color": {
                "r": 1,
                "g": 1,
                "b": 1,
                "a": 1
              }
            }
          ],
          "fills": [
            {
              "blendMode": "NORMAL",
              "visible": false,
              "type": "SOLID",
              "color": {
                "r": 1,
                "g": 1,
                "b": 1,
                "a": 1
              }
            }
          ],
          "strokes": [],
          "strokeWeight": 1,
          "strokeAlign": "INSIDE",
          "backgroundColor": {
            "r": 0,
            "g": 0,
            "b": 0,
            "a": 0
          },
          "absoluteBoundingBox": {
            "x": 356,
            "y": 3835,
            "width": 24,
            "height": 24
          },
          "absoluteRenderBounds": {
            "x": 356,
            "y": 3835,
            "width": 24,
            "height": 24
          },
          "constraints": {
            "vertical": "TOP",
            "horizontal": "LEFT"
          },
          "effects": [],
          "interactions": [],
          "complexStrokeProperties": {
            "strokeType": "BASIC"
          }
        }
      ],
      "blendMode": "PASS_THROUGH",
      "clipsContent": false,
      "background": [],
      "fills": [],
      "strokes": [],
      "rectangleCornerRadii": [
        0,
        0,
        0,
        0
      ],
      "cornerSmoothing": 0,
      "strokeWeight": 1,
      "strokeAlign": "INSIDE",
      "backgroundColor": {
        "r": 0,
        "g": 0,
        "b": 0,
        "a": 0
      },
      "absoluteBoundingBox": {
        "x": 0,
        "y": 3814,
        "width": 414,
        "height": 66
      },
      "absoluteRenderBounds": {
        "x": 0,
        "y": 3813,
        "width": 414,
        "height": 67
      },
      "constraints": {
        "vertical": "TOP",
        "horizontal": "LEFT"
      },
      "effects": [],
      "interactions": [],
      "complexStrokeProperties": {
        "strokeType": "BASIC"
      }
    },
    {
      "id": "253:258",
      "name": "image 14",
      "type": "RECTANGLE",
      "scrollBehavior": "SCROLLS",
      "blendMode": "PASS_THROUGH",
      "fills": [
        {
          "blendMode": "NORMAL",
          "type": "IMAGE",
          "scaleMode": "STRETCH",
          "imageRef": "f9413f433f70fdeb60355b5211825ac354659a69",
          "imageTransform": [
            [
              1,
              0,
              -2.220446049250313e-16
            ],
            [
              0,
              0.9033203721046448,
              0.07373046875
            ]
          ]
        }
      ],
      "strokes": [],
      "strokeWeight": 1,
      "strokeAlign": "INSIDE",
      "absoluteBoundingBox": {
        "x": 0,
        "y": 2984,
        "width": 414,
        "height": 809.6194458007812
      },
      "absoluteRenderBounds": {
        "x": 0,
        "y": 2984,
        "width": 414,
        "height": 809.619384765625
      },
      "constraints": {
        "vertical": "TOP",
        "horizontal": "LEFT"
      },
      "effects": [],
      "interactions": [],
      "complexStrokeProperties": {
        "strokeType": "BASIC"
      }
    }
  ],
  "blendMode": "PASS_THROUGH",
  "clipsContent": true,
  "background": [
    {
      "blendMode": "NORMAL",
      "type": "SOLID",
      "color": {
        "r": 0.9882352948188782,
        "g": 0.9921568632125854,
        "b": 0.9921568632125854,
        "a": 1
      }
    }
  ],
  "fills": [
    {
      "blendMode": "NORMAL",
      "type": "SOLID",
      "color": {
        "r": 0.9882352948188782,
        "g": 0.9921568632125854,
        "b": 0.9921568632125854,
        "a": 1
      }
    }
  ],
  "strokes": [],
  "strokeWeight": 1,
  "strokeAlign": "INSIDE",
  "backgroundColor": {
    "r": 0.9882352948188782,
    "g": 0.9921568632125854,
    "b": 0.9921568632125854,
    "a": 1
  },
  "absoluteBoundingBox": {
    "x": 0,
    "y": 2984,
    "width": 414,
    "height": 896
  },
  "absoluteRenderBounds": {
    "x": 0,
    "y": 2984,
    "width": 414,
    "height": 896
  },
  "constraints": {
    "vertical": "TOP",
    "horizontal": "LEFT"
  },
  "exportSettings": [
    {
      "suffix": "",
      "format": "PNG",
      "constraint": {
        "type": "SCALE",
        "value": 1
      }
    }
  ],
  "effects": [],
  "interactions": [],
  "complexStrokeProperties": {
    "strokeType": "BASIC"
  }
}
